vidi3d/__init__.py
vidi3d/animation.py
vidi3d/coordinates.py
vidi3d/core.py
vidi3d/definitions.py
vidi3d/helpers.py
vidi3d/image.py
vidi3d/navigation.py
vidi3d/plot.py
vidi3d/signals.py
vidi3d/viewers.py
vidi3d/compare/controls.py
vidi3d/compare/main.py
vidi3d/examples/crosscorrelation_example.py
vidi3d/examples/glm_example.py
vidi3d/examples/phantom.py
vidi3d/examples/simulation.py
vidi3d/examples/ttest_example.py
vidi3d/icons/lasso.png
vidi3d/icons/movie.png
vidi3d/imshow/controls.py
vidi3d/imshow/image4d.py
vidi3d/imshow/main.py
vidi3d-1.3.5.dist-info/LICENSE
vidi3d-1.3.5.dist-info/METADATA
vidi3d-1.3.5.dist-info/WHEEL
vidi3d-1.3.5.dist-info/top_level.txt
vidi3d-1.3.5.dist-info/RECORD
