Metadata-Version: 2.1
Name: vidi3d
Version: 1.3.5
Summary: Visualizes 3d/4d NumPy arrays using Matplotlib and PyQt5.
Home-page: https://github.com/AlanKuurstra/vidi3d
Author: Alan Kuurstra
Author-email: alankuurstra@gmail.com
Keywords: 3d,image,viewer,medical,numpy
Classifier: Programming Language :: Python :: 3
Classifier: License :: OSI Approved :: GNU General Public License v3 (GPLv3)
Requires-Python: >=3.8
License-File: LICENSE
Requires-Dist: numpy
Requires-Dist: PyQt5
Requires-Dist: matplotlib>=3.7
